LICENSE
echo1_coco_split/__init__.py
echo1_coco_split/echo1_coco_split.py
echo1_coco_split-0.1.5.dist-info/entry_points.txt
echo1_coco_split-0.1.5.dist-info/LICENSE
echo1_coco_split-0.1.5.dist-info/WHEEL
echo1_coco_split-0.1.5.dist-info/METADATA
echo1_coco_split-0.1.5.dist-info/RECORD
